hdl/roberts_core.v
//============================================================================
// roberts_core.v — Roberts Cross gradient computation (combinational)
//
// Takes a 2x2 pixel window and computes:
//   Gx = p00 - p11   (main diagonal difference)
//   Gy = p01 - p10   (anti-diagonal difference)
//   magnitude = |Gx| + |Gy|   (Manhattan approximation)
//   magnitude = min(magnitude, 255)  (saturate to 8-bit)
//   binary = (magnitude >= THRESHOLD) ? 255 : 0
//
// Pixel layout:
//   p00  p01    ← row R   (older row, from line buffer)
//   p10  p11    ← row R+1 (current row, direct input)
//
// Arithmetic matches the Python golden model in roberts_golden.py exactly.
//============================================================================

module roberts_core #(
    parameter THRESHOLD = 30
)(
    input  wire [7:0] p00,    // pixel[r][c]     — top-left
    input  wire [7:0] p01,    // pixel[r][c+1]   — top-right
    input  wire [7:0] p10,    // pixel[r+1][c]   — bottom-left
    input  wire [7:0] p11,    // pixel[r+1][c+1] — bottom-right
    output wire [7:0] gradient_out,
    output wire [7:0] binary_out
);

    // ── Step 1: Signed gradient computation ────────────────────────
    // Extend 8-bit unsigned pixels to 9-bit signed before subtraction.
    // Range of gx, gy: [-255, +255] — fits in 9 bits signed.
    wire signed [8:0] gx;
    wire signed [8:0] gy;

    assign gx = {1'b0, p00} - {1'b0, p11};   // main diagonal
    assign gy = {1'b0, p01} - {1'b0, p10};   // anti-diagonal

    // ── Step 2: Absolute values ────────────────────────────────────
    // Two's complement negation when sign bit is set.
    // Result range: [0, 255] — fits in 8 bits unsigned.
    wire [7:0] abs_gx;
    wire [7:0] abs_gy;

    assign abs_gx = gx[8] ? (~gx[7:0] + 8'd1) : gx[7:0];
    assign abs_gy = gy[8] ? (~gy[7:0] + 8'd1) : gy[7:0];

    // ── Step 3: Manhattan magnitude with saturation ────────────────
    // Sum range: [0, 510] — needs 9 bits.
    // Saturate to 255 if bit 8 is set.
    wire [8:0] sum;
    assign sum = {1'b0, abs_gx} + {1'b0, abs_gy};

    assign gradient_out = sum[8] ? 8'hFF : sum[7:0];

    // ── Step 4: Binary thresholding ────────────────────────────────
    assign binary_out = (gradient_out >= THRESHOLD) ? 8'hFF : 8'h00;

endmodule

hdl/line_buffer.v
//============================================================================
// line_buffer.v — Parameterized shift-register line buffer
//
// Delays an input pixel stream by exactly WIDTH clock cycles.
// Used to provide simultaneous access to pixels from adjacent rows
// in a streaming image processing pipeline.
//
// When valid_in is high, data shifts through a WIDTH-deep chain of
// flip-flops. The output presents the pixel that entered WIDTH clocks ago.
//============================================================================

module line_buffer #(
    parameter WIDTH  = 64,
    parameter DATA_W = 8
)(
    input  wire              clk,
    input  wire              rst,
    input  wire              valid_in,
    input  wire [DATA_W-1:0] data_in,
    output wire [DATA_W-1:0] data_out
);

    // Shift register array — exactly WIDTH stages
    reg [DATA_W-1:0] sr [0:WIDTH-1];
    integer i;

    always @(posedge clk) begin
        if (rst) begin
            for (i = 0; i < WIDTH; i = i + 1)
                sr[i] <= {DATA_W{1'b0}};
        end else if (valid_in) begin
            // New pixel enters stage 0
            sr[0] <= data_in;
            // All other stages shift forward
            for (i = 1; i < WIDTH; i = i + 1)
                sr[i] <= sr[i-1];
        end
        // When valid_in is low, all registers hold their current values
    end

    // Output is the oldest pixel in the chain
    assign data_out = sr[WIDTH-1];

endmodule

hdl/roberts_top.v
//============================================================================
// roberts_top.v — Roberts Cross edge detection top-level module
//
// Streaming architecture: one pixel in per clock, one pixel out per clock
// (after initial pipeline fill latency).
//
// Pipeline structure:
//   pixel_in → [line_buffer] → [2x2 sliding window regs] → [roberts_core] → outputs
//
// The line buffer delays by WIDTH clocks, giving access to row R (older)
// while the current input provides row R+1 (newer). Two-deep shift registers
// on each row provide the column-adjacent pixels for the 2x2 window.
//
// Output image dimensions: (WIDTH-1) x (HEIGHT-1)
// First valid output appears after WIDTH+1 valid input pixels.
//============================================================================

module roberts_top #(
    parameter WIDTH     = 64,
    parameter HEIGHT    = 64,
    parameter THRESHOLD = 30
)(
    input  wire       clk,
    input  wire       rst,
    input  wire       valid_in,
    input  wire [7:0] pixel_in,
    output reg        valid_out,
    output wire [7:0] gradient_out,
    output wire [7:0] binary_out
);

    // ── Line buffer: delays input stream by WIDTH clocks ───────────
    // Input:  current pixel (row R+1)
    // Output: pixel from same column, one row earlier (row R)
    wire [7:0] lb_out;

    line_buffer #(
        .WIDTH(WIDTH),
        .DATA_W(8)
    ) lb_inst (
        .clk(clk),
        .rst(rst),
        .valid_in(valid_in),
        .data_in(pixel_in),
        .data_out(lb_out)
    );

    // ── Sliding window shift registers (2 deep per row) ────────────
    // Each row has a 2-stage shift register.
    // Stage [0] = newest pixel (column c+1 in output terms)
    // Stage [1] = previous pixel (column c in output terms)
    //
    // row0 = older row (from line buffer = row R)
    // row1 = current row (direct input = row R+1)

    reg [7:0] row0_sr0, row0_sr1;   // row R:   sr0=newest, sr1=oldest
    reg [7:0] row1_sr0, row1_sr1;   // row R+1: sr0=newest, sr1=oldest

    always @(posedge clk) begin
        if (rst) begin
            row0_sr0 <= 8'd0;
            row0_sr1 <= 8'd0;
            row1_sr0 <= 8'd0;
            row1_sr1 <= 8'd0;
        end else if (valid_in) begin
            // Row R (from line buffer): shift
            row0_sr1 <= row0_sr0;
            row0_sr0 <= lb_out;

            // Row R+1 (current input): shift
            row1_sr1 <= row1_sr0;
            row1_sr0 <= pixel_in;
        end
    end

    // ── Window-to-core pixel mapping ───────────────────────────────
    //
    // Golden model:  gx = pixel[r][c]   - pixel[r+1][c+1]
    //                gy = pixel[r][c+1] - pixel[r+1][c]
    //
    // Register mapping:
    //   row0_sr1 = pixel[r][c]       (row R, older column)
    //   row0_sr0 = pixel[r][c+1]     (row R, newer column)
    //   row1_sr1 = pixel[r+1][c]     (row R+1, older column)
    //   row1_sr0 = pixel[r+1][c+1]   (row R+1, newer column)

    roberts_core #(
        .THRESHOLD(THRESHOLD)
    ) core_inst (
        .p00(row0_sr1),   // pixel[r][c]
        .p01(row0_sr0),   // pixel[r][c+1]
        .p10(row1_sr1),   // pixel[r+1][c]
        .p11(row1_sr0),   // pixel[r+1][c+1]
        .gradient_out(gradient_out),
        .binary_out(binary_out)
    );

    // ── Valid output control ───────────────────────────────────────
    // We track:
    //   pixel_count: total valid_in pulses received (0-based)
    //   col_count:   column position in current input row (0 to WIDTH-1)
    //
    // The line buffer needs WIDTH valid inputs to fill completely.
    // After that, lb_out presents valid row R data.
    // The shift registers need 1 additional clock to have 2 valid columns.
    // So: first valid output at pixel_count == WIDTH+1 (0-indexed), i.e.
    // after receiving the (WIDTH+2)th pixel... but let's think in terms of
    // when the window is fully populated:
    //
    //   - After WIDTH inputs: lb_out is valid (row 0, col 0)
    //   - That lb_out enters row0_sr0 on the same clock
    //   - On the NEXT clock (input WIDTH+1): row0_sr1 gets the first lb_out,
    //     row0_sr0 gets the second lb_out. Now we have 2 columns from row 0.
    //   - At this moment col_count = (WIDTH+1) % WIDTH = 1
    //
    // Output is valid when:
    //   1. pixel_count >= WIDTH + 1  (pipeline filled)
    //   2. col_count >= 1            (have 2 columns in shift registers)
    //
    // Output is NOT valid on the first column of each row (col_count == 0)
    // because the shift register only contains one column value.
    //
    // Total output pixels per row: WIDTH - 1
    // Total output rows: HEIGHT - 1
    // Total output pixels: (WIDTH-1) repeated (HEIGHT-1) times via addition

    reg [31:0] pixel_count;
    reg [15:0] col_count;

    always @(posedge clk) begin
        if (rst) begin
            pixel_count <= 32'd0;
            col_count   <= 16'd0;
            valid_out   <= 1'b0;
        end else if (valid_in) begin
            pixel_count <= pixel_count + 1;

            // Column counter: wraps at WIDTH
            if (col_count == WIDTH - 1)
                col_count <= 16'd0;
            else
                col_count <= col_count + 1;

            // Assert valid_out when pipeline is full and we have 2 columns
            if (pixel_count >= WIDTH && col_count != 0)
                valid_out <= 1'b1;
            else
                valid_out <= 1'b0;
        end else begin
            valid_out <= 1'b0;
        end
    end

endmodule

hdl/tb_roberts.v
// IMG_WIDTH, IMG_HEIGHT, IMG_THRESHOLD can be set via iverilog -D flags.
// NO_VCD disables VCD generation (faster; recommended for production use).
`ifndef IMG_WIDTH
  `define IMG_WIDTH 64
`endif
`ifndef IMG_HEIGHT
  `define IMG_HEIGHT 64
`endif
`ifndef IMG_THRESHOLD
  `define IMG_THRESHOLD 30
`endif

`timescale 1ns / 1ps

module tb_roberts;

    // Constant multiply used to size localparams without a * operator
    function integer multiply;
        input integer a, b;
        integer i;
        begin
            multiply = 0;
            for (i = 0; i < b; i = i + 1)
                multiply = multiply + a;
        end
    endfunction

    localparam WIDTH      = `IMG_WIDTH;
    localparam HEIGHT     = `IMG_HEIGHT;
    localparam THRESHOLD  = `IMG_THRESHOLD;
    localparam TOTAL_PX   = multiply(WIDTH, HEIGHT);
    localparam OUT_WIDTH  = WIDTH  - 1;
    localparam OUT_HEIGHT = HEIGHT - 1;
    localparam OUT_PIXELS = multiply(OUT_WIDTH, OUT_HEIGHT);

    // ── Clock ──────────────────────────────────────────────────────
    reg clk;
    always #5 clk = ~clk;

    // ── DUT signals ────────────────────────────────────────────────
    reg        rst;
    reg        valid_in;
    reg  [7:0] pixel_in;
    wire       valid_out;
    wire [7:0] gradient_out;
    wire [7:0] binary_out;

    reg [7:0] pixel_mem [0:TOTAL_PX-1];

    integer out_file;
    integer out_count;
    integer i;

    roberts_top #(
        .WIDTH(WIDTH),
        .HEIGHT(HEIGHT),
        .THRESHOLD(THRESHOLD)
    ) dut (
        .clk(clk),
        .rst(rst),
        .valid_in(valid_in),
        .pixel_in(pixel_in),
        .valid_out(valid_out),
        .gradient_out(gradient_out),
        .binary_out(binary_out)
    );

    // ── Stimulus ───────────────────────────────────────────────────
    initial begin
`ifndef NO_VCD
        $dumpfile("roberts.vcd");
        $dumpvars(0, tb_roberts);
`endif
        $readmemh("image.hex", pixel_mem);
        $display("Loaded %0d pixels from image.hex", TOTAL_PX);

        out_file = $fopen("output_roberts.hex", "w");
        if (out_file == 0) begin
            $display("ERROR: Could not open output_roberts.hex");
            $finish;
        end
        out_count = 0;

        clk      = 0;
        rst      = 1;
        valid_in = 0;
        pixel_in = 8'd0;

        @(posedge clk); #1;
        @(posedge clk); #1;
        @(posedge clk); #1;
        rst = 0;
        @(posedge clk); #1;

        for (i = 0; i < TOTAL_PX; i = i + 1) begin
            @(posedge clk); #1;
            valid_in = 1;
            pixel_in = pixel_mem[i];
        end

        @(posedge clk); #1;
        valid_in = 0;
        pixel_in = 8'd0;
        repeat (10) @(posedge clk);

        $fclose(out_file);
        $display("Simulation complete: %0d output pixels written to output_roberts.hex", out_count);
        $display("Expected: %0d  (= %0d x %0d)", OUT_PIXELS, OUT_WIDTH, OUT_HEIGHT);
        if (out_count == OUT_PIXELS)
            $display("STATUS: PIXEL COUNT OK");
        else
            $display("STATUS: PIXEL COUNT MISMATCH");
        $finish;
    end

    // ── Output capture ─────────────────────────────────────────────
    always @(posedge clk) begin
        if (valid_out && !rst) begin
            $fwrite(out_file, "%02X\n", gradient_out);
            out_count = out_count + 1;
        end
    end

endmodule

hdl/roberts.vcd
$date
	Sun May 10 11:38:25 2026
$end
$version
	Icarus Verilog
$end
$timescale
	1ps
$end
$scope module tb_roberts $end
$var wire 1 ! valid_out $end
$var wire 8 " gradient_out [7:0] $end
$var wire 8 # binary_out [7:0] $end
$var parameter 32 $ HEIGHT $end
$var parameter 33 % OUT_HEIGHT $end
$var parameter 32 & OUT_PIXELS $end
$var parameter 33 ' OUT_WIDTH $end
$var parameter 32 ( THRESHOLD $end
$var parameter 32 ) TOTAL_PX $end
$var parameter 32 * WIDTH $end
$var reg 1 + clk $end
$var reg 8 , pixel_in [7:0] $end
$var reg 1 - rst $end
$var reg 1 . valid_in $end
$var integer 32 / i [31:0] $end
$var integer 32 0 out_count [31:0] $end
$var integer 32 1 out_file [31:0] $end
$scope function multiply $end
$var integer 32 2 a [31:0] $end
$var integer 32 3 b [31:0] $end
$var integer 32 4 i [31:0] $end
$upscope $end
$scope module dut $end
$var wire 1 + clk $end
$var wire 8 5 pixel_in [7:0] $end
$var wire 1 - rst $end
$var wire 1 . valid_in $end
$var wire 8 6 lb_out [7:0] $end
$var wire 8 7 gradient_out [7:0] $end
$var wire 8 8 binary_out [7:0] $end
$var parameter 32 9 HEIGHT $end
$var parameter 32 : THRESHOLD $end
$var parameter 32 ; WIDTH $end
$var reg 16 < col_count [15:0] $end
$var reg 32 = pixel_count [31:0] $end
$var reg 8 > row0_sr0 [7:0] $end
$var reg 8 ? row0_sr1 [7:0] $end
$var reg 8 @ row1_sr0 [7:0] $end
$var reg 8 A row1_sr1 [7:0] $end
$var reg 1 ! valid_out $end
$scope module core_inst $end
$var wire 8 B p00 [7:0] $end
$var wire 8 C p01 [7:0] $end
$var wire 8 D p10 [7:0] $end
$var wire 8 E p11 [7:0] $end
$var wire 9 F sum [8:0] $end
$var wire 9 G gy [8:0] $end
$var wire 9 H gx [8:0] $end
$var wire 8 I gradient_out [7:0] $end
$var wire 8 J binary_out [7:0] $end
$var wire 8 K abs_gy [7:0] $end
$var wire 8 L abs_gx [7:0] $end
$var parameter 32 M THRESHOLD $end
$upscope $end
$scope module lb_inst $end
$var wire 1 + clk $end
$var wire 8 N data_in [7:0] $end
$var wire 8 O data_out [7:0] $end
$var wire 1 - rst $end
$var wire 1 . valid_in $end
$var parameter 32 P DATA_W $end
$var parameter 32 Q WIDTH $end
$var integer 32 R i [31:0] $end
$upscope $end
$upscope $end
$upscope $end
$enddefinitions $end
$comment Show the parameter values. $end
$dumpall
b1000000 Q
b1000 P
b11110 M
b1000000 ;
b11110 :
b1000000 9
b1000000 *
b1000000000000 )
b11110 (
b111111 '
b111110000001 &
b111111 %
b1000000 $
$end
#0
$dumpvars
bx R
bx O
b0 N
bx L
bx K
bx J
bx I
bx H
bx G
bx F
bx E
bx D
bx C
bx B
bx A
bx @
bx ?
bx >
bx =
bx <
bx 8
bx 7
bx 6
b0 5
bx 4
bx 3
bx 2
b10000000000000000000000000000011 1
b0 0
bx /
0.
1-
b0 ,
0+
bx #
bx "
x!
$end
#5000
b0 #
b0 8
b0 J
b0 "
b0 7
b0 I
b0 F
b0 K
b0 L
b0 6
b0 O
b0 G
b0 A
b0 D
b0 H
b0 @
b0 E
b0 ?
b0 B
b0 >
b0 C
0!
b0 <
b0 =
b1000000 R
1+
#10000
0+
#15000
b1000000 R
1+
#20000
0+
#25000
b1000000 R
1+
#26000
0-
#30000
0+
#35000
1+
#36000
b0 /
#40000
0+
#45000
1+
#46000
b1 /
b101101 ,
b101101 5
b101101 N
1.
#50000
0+
#55000
b11111111 #
b11111111 8
b11111111 J
b101101 "
b101101 7
b101101 I
b101101 F
b101101 L
b1 <
b1 =
b111010011 H
b101101 @
b101101 E
b1000000 R
1+
#56000
b10 /
b110010 ,
b110010 5
b110010 N
#60000
0+
#65000
b1011111 "
b1011111 7
b1011111 I
b110010 L
b1011111 F
b101101 K
b111001110 H
b110010 @
b110010 E
b111010011 G
b101101 A
b101101 D
b10 <
b10 =
b1000000 R
1+
#66000
b11 /
b101011 ,
b101011 5
b101011 N
#70000
0+
#75000
b1011101 "
b1011101 7
b1011101 I
b101011 L
b1011101 F
b110010 K
b11 <
b11 =
b111010101 H
b101011 @
b101011 E
b111001110 G
b110010 A
b110010 D
b1000000 R
1+
#76000
b100 /
b100010 ,
b100010 5
b100010 N
#80000
0+
#85000
b1001101 "
b1001101 7
b1001101 I
b100010 L
b1001101 F
b101011 K
b111011110 H
b100010 @
b100010 E
b111010101 G
b101011 A
b101011 D
b100 <
b100 =
b1000000 R
1+
#86000
b101 /
b100011 ,
b100011 5
b100011 N
#90000
0+
#95000
b1000101 "
b1000101 7
b1000101 I
b100011 L
b1000101 F
b100010 K
b101 <
b101 =
b111011101 H
b100011 @
b100011 E
b111011110 G
b100010 A
b100010 D
b1000000 R
1+
#96000
b110 /
b101010 ,
b101010 5
b101010 N
#100000
0+
#105000
b1001101 "
b1001101 7
b1001101 I
b101010 L
b1001101 F
b100011 K
b111010110 H
b101010 @
b101010 E
b111011101 G
b100011 A
b100011 D
b110 <
b110 =
b1000000 R
1+
#106000
b111 /
b110100 ,
b110100 5
b110100 N
#110000
0+
#115000
b1011110 "
b1011110 7
b1011110 I
b110100 L
b1011110 F
b101010 K
b111 <
b111 =
b111001100 H
b110100 @
b110100 E
b111010110 G
b101010 A
b101010 D
b1000000 R
1+
#116000
b1000 /
b110110 ,
b110110 5
b110110 N
#120000
0+
#125000
b1101010 "
b1101010 7
b1101010 I
b110110 L
b1101010 F
b110100 K
b111001010 H
b110110 @
b110110 E
b111001100 G
b110100 A
b110100 D
b1000 <
b1000 =
b1000000 R
1+
#126000
b1001 /
#130000
0+
#135000
b1101100 "
b1101100 7
b1101100 I
b1101100 F
b110110 K
b1001 <
b1001 =
b111001010 G
b110110 A
b110110 D
b1000000 R
1+
#136000
b1010 /
b110111 ,
b110111 5
b110111 N
#140000
0+
#145000
b1101101 "
b1101101 7
b1101101 I
b1101101 F
b110111 L
b111001001 H
b110111 @
b110111 E
b1010 <
b1010 =
b1000000 R
1+
#146000
b1011 /
b110011 ,
b110011 5
b110011 N
#150000
0+
#155000
b1101010 "
b1101010 7
b1101010 I
b110011 L
b1101010 F
b110111 K
b1011 <
b1011 =
b111001101 H
b110011 @
b110011 E
b111001001 G
b110111 A
b110111 D
b1000000 R
1+
#156000
b1100 /
b101100 ,
b101100 5
b101100 N
#160000
0+
#165000
b1011111 "
b1011111 7
b1011111 I
b101100 L
b1011111 F
b110011 K
b111010100 H
b101100 @
b101100 E
b111001101 G
b110011 A
b110011 D
b1100 <
b1100 =
b1000000 R
1+
#166000
b1101 /
b101010 ,
b101010 5
b101010 N
#170000
0+
#175000
b1010110 "
b1010110 7
b1010110 I
b101010 L
b1010110 F
b101100 K
b1101 <
b1101 =
b111010110 H
b101010 @
b101010 E
b111010100 G
b101100 A
b101100 D
b1000000 R
1+
#176000
b1110 /
b101011 ,
b101011 5
b101011 N
#180000
0+
#185000
b1010101 "
b1010101 7
b1010101 I
b101011 L
b1010101 F
b101010 K
b111010101 H
b101011 @
b101011 E
b111010110 G
b101010 A
b101010 D
b1110 <
b1110 =
b1000000 R
1+
#186000
b1111 /
b101100 ,
b101100 5
b101100 N
#190000
0+
#195000
b1010111 "
b1010111 7
b1010111 I
b101100 L
b1010111 F
b101011 K
b1111 <
b1111 =
b111010100 H
b101100 @
b101100 E
b111010101 G
b101011 A
b101011 D
b1000000 R
1+
#196000
b10000 /
b101101 ,
b101101 5
b101101 N
#200000
0+
#205000
b1011001 "
b1011001 7
b1011001 I
b101101 L
b1011001 F
b101100 K
b111010011 H
b101101 @
b101101 E
b111010100 G
b101100 A
b101100 D
b10000 <
b10000 =
b1000000 R
1+
#206000
b10001 /
b101110 ,
b101110 5
b101110 N
#210000
0+
#215000
b1011011 "
b1011011 7
b1011011 I
b101110 L
b1011011 F
b101101 K
b10001 <
b10001 =
b111010010 H
b101110 @
b101110 E
b111010011 G
b101101 A
b101101 D
b1000000 R
1+
#216000
b10010 /
b101111 ,
b101111 5
b101111 N
#220000
0+
#225000
b1011101 "
b1011101 7
b1011101 I
b101111 L
b1011101 F
b101110 K
b111010001 H
b101111 @
b101111 E
b111010010 G
b101110 A
b101110 D
b10010 <
b10010 =
b1000000 R
1+
#226000
b10011 /
b110000 ,
b110000 5
b110000 N
#230000
0+
#235000
b1011111 "
b1011111 7
b1011111 I
b110000 L
b1011111 F
b101111 K
b10011 <
b10011 =
b111010000 H
b110000 @
b110000 E
b111010001 G
b101111 A
b101111 D
b1000000 R
1+
#236000
b10100 /
b101101 ,
b101101 5
b101101 N
#240000
0+
#245000
b1011101 "
b1011101 7
b1011101 I
b101101 L
b1011101 F
b110000 K
b111010011 H
b101101 @
b101101 E
b111010000 G
b110000 A
b110000 D
b10100 <
b10100 =
b1000000 R
1+
#246000
b10101 /
b100100 ,
b100100 5
b100100 N
#250000
0+
#255000
b1010001 "
b1010001 7
b1010001 I
b100100 L
b1010001 F
b101101 K
b10101 <
b10101 =
b111011100 H
b100100 @
b100100 E
b111010011 G
b101101 A
b101101 D
b1000000 R
1+
#256000
b10110 /
b100010 ,
b100010 5
b100010 N
#260000
0+
#265000
b1000110 "
b1000110 7
b1000110 I
b100010 L
b1000110 F
b100100 K
b111011110 H
b100010 @
b100010 E
b111011100 G
b100100 A
b100100 D
b10110 <
b10110 =
b1000000 R
1+
#266000
b10111 /
b11100 ,
b11100 5
b11100 N
#270000
0+
#275000
b111110 "
b111110 7
b111110 I
b11100 L
b111110 F
b100010 K
b10111 <
b10111 =
b111100100 H
b11100 @
b11100 E
b111011110 G
b100010 A
b100010 D
b1000000 R
1+
#276000
b11000 /
b1101 ,
b1101 5
b1101 N
#280000
0+
#285000
b101001 "
b101001 7
b101001 I
b1101 L
b101001 F
b11100 K
b111110011 H
b1101 @
b1101 E
b111100100 G
b11100 A
b11100 D
b11000 <
b11000 =
b1000000 R
1+
#286000
b11001 /
b1110 ,
b1110 5
b1110 N
#290000
0+
#295000
b0 #
b0 8
b0 J
b11011 "
b11011 7
b11011 I
b1110 L
b11011 F
b1101 K
b11001 <
b11001 =
b111110010 H
b1110 @
b1110 E
b111110011 G
b1101 A
b1101 D
b1000000 R
1+
#296000
b11010 /
b10100 ,
b10100 5
b10100 N
#300000
0+
#305000
b11111111 #
b11111111 8
b11111111 J
b100010 "
b100010 7
b100010 I
b10100 L
b100010 F
b1110 K
b111101100 H
b10100 @
b10100 E
b111110010 G
b1110 A
b1110 D
b11010 <
b11010 =
b1000000 R
1+
#306000
b11011 /
#310000
0+
#315000
b101000 "
b101000 7
b101000 I
b101000 F
b10100 K
b11011 <
b11011 =
b111101100 G
b10100 A
b10100 D
b1000000 R
1+
#316000
b11100 /
b10011 ,
b10011 5
b10011 N
#320000
0+
#325000
b100111 "
b100111 7
b100111 I
b100111 F
b10011 L
b111101101 H
b10011 @
b10011 E
b11100 <
b11100 =
b1000000 R
1+
#326000
b11101 /
b10000 ,
b10000 5
b10000 N
#330000
0+
#335000
b100011 "
b100011 7
b100011 I
b10000 L
b100011 F
b10011 K
b11101 <
b11101 =
b111110000 H
b10000 @
b10000 E
b111101101 G
b10011 A
b10011 D
b1000000 R
1+
#336000
b11110 /
b1110 ,
b1110 5
b1110 N
#340000
0+
#345000
b11110 "
b11110 7
b11110 I
b1110 L
b11110 F
b10000 K
b111110010 H
b1110 @
b1110 E
b111110000 G
b10000 A
b10000 D
b11110 <
b11110 =
b1000000 R
1+
#346000
b11111 /
b11001 ,
b11001 5
b11001 N
#350000
0+
#355000
b100111 "
b100111 7
b100111 I
b11001 L
b100111 F
b1110 K
b11111 <
b11111 =
b111100111 H
b11001 @
b11001 E
b111110010 G
b1110 A
b1110 D
b1000000 R
1+
#356000
b100000 /
b101010 ,
b101010 5
b101010 N
#360000
0+
#365000
b1000011 "
b1000011 7
b1000011 I
b101010 L
b1000011 F
b11001 K
b111010110 H
b101010 @
b101010 E
b111100111 G
b11001 A
b11001 D
b100000 <
b100000 =
b1000000 R
1+
#366000
b100001 /
b11110 ,
b11110 5
b11110 N
#370000
0+
#375000
b1001000 "
b1001000 7
b1001000 I
b11110 L
b1001000 F
b101010 K
b100001 <
b100001 =
b111100010 H
b11110 @
b11110 E
b111010110 G
b101010 A
b101010 D
b1000000 R
1+
#376000
b100010 /
b100001 ,
b100001 5
b100001 N
#380000
0+
#385000
b111111 "
b111111 7
b111111 I
b100001 L
b111111 F
b11110 K
b111011111 H
b100001 @
b100001 E
b111100010 G
b11110 A
b11110 D
b100010 <
b100010 =
b1000000 R
1+
#386000
b100011 /
b110001 ,
b110001 5
b110001 N
#390000
0+
#395000
b1010010 "
b1010010 7
b1010010 I
b110001 L
b1010010 F
b100001 K
b100011 <
b100011 =
b111001111 H
b110001 @
b110001 E
b111011111 G
b100001 A
b100001 D
b1000000 R
1+
#396000
b100100 /
b100101 ,
b100101 5
b100101 N
#400000
0+
#405000
b1010110 "
b1010110 7
b1010110 I
b100101 L
b1010110 F
b110001 K
b111011011 H
b100101 @
b100101 E
b111001111 G
b110001 A
b110001 D
b100100 <
b100100 =
b1000000 R
1+
#406000
b100101 /
#410000
0+
#415000
b1001010 "
b1001010 7
b1001010 I
b1001010 F
b100101 K
b100101 <
b100101 =
b111011011 G
b100101 A
b100101 D
b1000000 R
1+
#416000
b100110 /
b11101 ,
b11101 5
b11101 N
#420000
0+
#425000
b1000010 "
b1000010 7
b1000010 I
b1000010 F
b11101 L
b111100011 H
b11101 @
b11101 E
b100110 <
b100110 =
b1000000 R
1+
#426000
b100111 /
b100101 ,
b100101 5
b100101 N
#430000
0+
#435000
b100101 L
b1000010 F
b11101 K
b100111 <
b100111 =
b111011011 H
b100101 @
b100101 E
b111100011 G
b11101 A
b11101 D
b1000000 R
1+
#436000
b101000 /
b110010 ,
b110010 5
b110010 N
#440000
0+
#445000
b1010111 "
b1010111 7
b1010111 I
b110010 L
b1010111 F
b100101 K
b111001110 H
b110010 @
b110010 E
b111011011 G
b100101 A
b100101 D
b101000 <
b101000 =
b1000000 R
1+
#446000
b101001 /
b11000 ,
b11000 5
b11000 N
#450000
0+
#455000
b1001010 "
b1001010 7
b1001010 I
b11000 L
b1001010 F
b110010 K
b101001 <
b101001 =
b111101000 H
b11000 @
b11000 E
b111001110 G
b110010 A
b110010 D
b1000000 R
1+
#456000
b101010 /
b100000 ,
b100000 5
b100000 N
#460000
0+
#465000
b111000 "
b111000 7
b111000 I
b100000 L
b111000 F
b11000 K
b111100000 H
b100000 @
b100000 E
b111101000 G
b11000 A
b11000 D
b101010 <
b101010 =
b1000000 R
1+
#466000
b101011 /
b100011 ,
b100011 5
b100011 N
#470000
0+
#475000
b1000011 "
b1000011 7
b1000011 I
b100011 L
b1000011 F
b100000 K
b101011 <
b101011 =
b111011101 H
b100011 @
b100011 E
b111100000 G
b100000 A
b100000 D
b1000000 R
1+
#476000
b101100 /
b101010 ,
b101010 5
b101010 N
#480000
0+
#485000
b1001101 "
b1001101 7
b1001101 I
b101010 L
b1001101 F
b100011 K
b111010110 H
b101010 @
b101010 E
b111011101 G
b100011 A
b100011 D
b101100 <
b101100 =
b1000000 R
1+
#486000
b101101 /
b110010 ,
b110010 5
b110010 N
#490000
0+
#495000
b1011100 "
b1011100 7
b1011100 I
b110010 L
b1011100 F
b101010 K
b101101 <
b101101 =
b111001110 H
b110010 @
b110010 E
b111010110 G
b101010 A
b101010 D
b1000000 R
1+
#496000
b101110 /
b101010 ,
b101010 5
b101010 N
#500000
0+
#505000
b101010 L
b1011100 F
b110010 K
b111010110 H
b101010 @
b101010 E
b111001110 G
b110010 A
b110010 D
b101110 <
b101110 =
b1000000 R
1+
#506000
b101111 /
b110010 ,
b110010 5
b110010 N
#510000
0+
#515000
b110010 L
b1011100 F
b101010 K
b101111 <
b101111 =
b111001110 H
b110010 @
b110010 E
b111010110 G
b101010 A
b101010 D
b1000000 R
1+
#516000
b110000 /
b110011 ,
b110011 5
b110011 N
#520000
0+
#525000
b1100101 "
b1100101 7
b1100101 I
b110011 L
b1100101 F
b110010 K
b111001101 H
b110011 @
b110011 E
b111001110 G
b110010 A
b110010 D
b110000 <
b110000 =
b1000000 R
1+
#526000
b110001 /
#530000
0+
#535000
b1100110 "
b1100110 7
b1100110 I
b1100110 F
b110011 K
b110001 <
b110001 =
b111001101 G
b110011 A
b110011 D
b1000000 R
1+
#536000
b110010 /
b111000 ,
b111000 5
b111000 N
#540000
0+
#545000
b1101011 "
b1101011 7
b1101011 I
b1101011 F
b111000 L
b111001000 H
b111000 @
b111000 E
b110010 <
b110010 =
b1000000 R
1+
#546000
b110011 /
b100011 ,
b100011 5
b100011 N
#550000
0+
#555000
b1011011 "
b1011011 7
b1011011 I
b100011 L
b1011011 F
b111000 K
b110011 <
b110011 =
b111011101 H
b100011 @
b100011 E
b111001000 G
b111000 A
b111000 D
b1000000 R
1+
#556000
b110100 /
b10011 ,
b10011 5
b10011 N
#560000
0+
#565000
b110110 "
b110110 7
b110110 I
b10011 L
b110110 F
b100011 K
b111101101 H
b10011 @
b10011 E
b111011101 G
b100011 A
b100011 D
b110100 <
b110100 =
b1000000 R
1+
#566000
b110101 /
b110101 ,
b110101 5
b110101 N
#570000
0+
#575000
b1001000 "
b1001000 7
b1001000 I
b110101 L
b1001000 F
b10011 K
b110101 <
b110101 =
b111001011 H
b110101 @
b110101 E
b111101101 G
b10011 A
b10011 D
b1000000 R
1+
#576000
b110110 /
b1110011 ,
b1110011 5
b1110011 N
#580000
0+
#585000
b10101000 "
b10101000 7
b10101000 I
b1110011 L
b10101000 F
b110101 K
b110001101 H
b1110011 @
b1110011 E
b111001011 G
b110101 A
b110101 D
b110110 <
b110110 =
b1000000 R
1+
#586000
b110111 /
b1111101 ,
b1111101 5
b1111101 N
#590000
0+
#595000
b11110000 "
b11110000 7
b11110000 I
b1111101 L
b11110000 F
b1110011 K
b110111 <
b110111 =
b110000011 H
b1111101 @
b1111101 E
b110001101 G
b1110011 A
b1110011 D
b1000000 R
1+
#596000
b111000 /
b1110111 ,
b1110111 5
b1110111 N
#600000
0+
#605000
b11110100 "
b11110100 7
b11110100 I
b1110111 L
b11110100 F
b1111101 K
b110001001 H
b1110111 @
b1110111 E
b110000011 G
b1111101 A
b1111101 D
b111000 <
b111000 =
b1000000 R
1+
#606000
b111001 /
b10001101 ,
b10001101 5
b10001101 N
#610000
0+
#615000
b11111111 "
b11111111 7
b11111111 I
b10001101 L
b100000100 F
b1110111 K
b111001 <
b111001 =
b101110011 H
b10001101 @
b10001101 E
b110001001 G
b1110111 A
b1110111 D
b1000000 R
1+
#616000
b111010 /
b10010110 ,
b10010110 5
b10010110 N
#620000
0+
