hdl/sobel.v
// ============================================================
// sobel.v — Streaming Sobel Edge Detector
// ============================================================
// Pixels stream in one-per-clock, row-major (left to right, top to bottom).
// Two line buffers store previous rows so we always have a 3x3 window.
//
//  Pipeline (2-stage):
//
//  Stage 0: Window Load (clocked)
//  ──────────────────────────────
//  pixel_in ──┬──> [line_buf1] ──> [line_buf0]
//             |        |                |
//           row2     row1             row0
//             └────────┴────────────────┘
//                     3x3 window regs
//
//  Stage 1: Compute + Threshold (comb -> registered output)
//  ────────────────────────────────────────────────────────
//                    Gx, Gy  (combinational)
//                  |Gx|+|Gy| (combinational)
//                  threshold -> pixel_out, out_valid (registered)
//
// After the window fills (row >= 2, col >= 2), the output becomes
// valid one cycle later.  Output image is (IMG_W-2) x (IMG_H-2).
// ============================================================

module sobel #(
    parameter IMG_W     = 64,
    parameter IMG_H     = 64,
    parameter THRESHOLD = 80
)(
    input  wire        clk,
    input  wire        rst,
    input  wire [7:0]  pixel_in,
    input  wire        pixel_valid,
    output reg  [7:0]  pixel_out,
    output reg         out_valid
);

    // -- Position counters --
    reg [15:0] col_cnt;
    reg [15:0] row_cnt;

    // -- Line buffers (RAM) --
    reg [7:0] lb0 [0:IMG_W-1];   // row from 2 rows ago
    reg [7:0] lb1 [0:IMG_W-1];   // row from 1 row  ago

    // -- 3x3 window registers --
    //   p00 p01 p02    <- row 0 (oldest)
    //   p10 p11 p12    <- row 1
    //   p20 p21 p22    <- row 2 (newest / current)
    reg [7:0] p00, p01, p02;
    reg [7:0] p10, p11, p12;
    reg [7:0] p20, p21, p22;

    // -- Pipeline valid flag --
    // Registered so output fires 1 cycle after window loads,
    // giving the combinational gx/gy/mag time to settle on
    // the updated window values.
    reg win_filled;

    // -- Gradient computation (combinational) --
    // Max |Gx| or |Gy| = 255+510+255 = 1020 -> 11 bits + sign
    wire signed [11:0] gx;
    wire signed [11:0] gy;
    wire        [11:0] abs_gx;
    wire        [11:0] abs_gy;
    wire        [11:0] mag;

    // Gx = right_col - left_col
    //     (p02 + 2*p12 + p22) - (p00 + 2*p10 + p20)
    assign gx = ({4'd0, p02} + ({4'd0, p12} << 1) + {4'd0, p22})
              - ({4'd0, p00} + ({4'd0, p10} << 1) + {4'd0, p20});

    // Gy = bottom_row - top_row
    //     (p20 + 2*p21 + p22) - (p00 + 2*p01 + p02)
    assign gy = ({4'd0, p20} + ({4'd0, p21} << 1) + {4'd0, p22})
              - ({4'd0, p00} + ({4'd0, p01} << 1) + {4'd0, p02});

    // Absolute value (two's complement negate if negative)
    assign abs_gx = gx[11] ? (~gx + 12'd1) : gx;
    assign abs_gy = gy[11] ? (~gy + 12'd1) : gy;

    // Hardware-friendly magnitude: |Gx| + |Gy|
    assign mag = abs_gx + abs_gy;

    // -- Stage 0: Window load + line buffer update --
    integer i;

    always @(posedge clk) begin
        if (rst) begin
            col_cnt <= 0;
            row_cnt <= 0;
            p00 <= 0; p01 <= 0; p02 <= 0;
            p10 <= 0; p11 <= 0; p12 <= 0;
            p20 <= 0; p21 <= 0; p22 <= 0;
            win_filled <= 0;
            for (i = 0; i < IMG_W; i = i + 1) begin
                lb0[i] <= 0;
                lb1[i] <= 0;
            end
        end else if (pixel_valid) begin
            // Shift 3x3 window: new column enters from the right
            p00 <= p01;  p01 <= p02;  p02 <= lb0[col_cnt];
            p10 <= p11;  p11 <= p12;  p12 <= lb1[col_cnt];
            p20 <= p21;  p21 <= p22;  p22 <= pixel_in;

            // Cascade line buffers down
            lb0[col_cnt] <= lb1[col_cnt];
            lb1[col_cnt] <= pixel_in;

            // Advance position
            if (col_cnt == IMG_W - 1) begin
                col_cnt <= 0;
                row_cnt <= row_cnt + 1;
            end else begin
                col_cnt <= col_cnt + 1;
            end

            // Flag: the window will be valid after this cycle's
            // non-blocking assignments complete, so we register
            // the flag — the output stage reads it next cycle.
            win_filled <= (row_cnt >= 2) && (col_cnt >= 2);
        end else begin
            win_filled <= 0;
        end
    end

    // -- Stage 1: Threshold + output register --
    // Fires one cycle after win_filled, so gx/gy/mag
    // are computed from the fully-updated window.
    always @(posedge clk) begin
        if (rst) begin
            pixel_out <= 0;
            out_valid <= 0;
        end else begin
            out_valid <= win_filled;
            if (win_filled) begin
                pixel_out <= (mag > THRESHOLD) ? 8'hFF : 8'h00;
            end
        end
    end

endmodule

hdl/sobel_tb.v
// ============================================================
// sobel_tb.v — Testbench for Sobel Edge Detector
// ============================================================
// 1. Reads grayscale pixels from input.hex ($readmemh)
// 2. Streams one pixel per clock into the sobel module
// 3. Captures output pixels when out_valid is high
// 4. Writes results to output.hex
// 5. Dumps VCD waveform for gtkwave
// ============================================================

// IMG_WIDTH / IMG_HEIGHT can be passed at compile time via iverilog -D flags.
// Defaults match the standard 64x64 test images generated by generate_test_images.py.
`ifndef IMG_WIDTH
  `define IMG_WIDTH 64
`endif
`ifndef IMG_HEIGHT
  `define IMG_HEIGHT 64
`endif

`timescale 1ns / 1ps

module sobel_tb;

    localparam W = `IMG_WIDTH;
    localparam H = `IMG_HEIGHT;
    localparam NUM_PIXELS = W * H;
    localparam THRESHOLD  = 80;

    // -- Clock & reset --
    reg clk;
    reg rst;

    // -- DUT signals --
    reg  [7:0] pixel_in;
    reg        pixel_valid;
    wire [7:0] pixel_out;
    wire       out_valid;

    // -- Pixel storage --
    reg [7:0] img_in  [0:NUM_PIXELS-1];

    // -- Output capture --
    integer out_file;
    integer out_count;

    // -- Pixel feed counter --
    integer feed_idx;

    // -- Instantiate the Sobel module --
    sobel #(
        .IMG_W     (W),
        .IMG_H     (H),
        .THRESHOLD (THRESHOLD)
    ) dut (
        .clk         (clk),
        .rst         (rst),
        .pixel_in    (pixel_in),
        .pixel_valid (pixel_valid),
        .pixel_out   (pixel_out),
        .out_valid   (out_valid)
    );

    // -- Clock generation: 10 ns period --
    initial clk = 0;
    always #5 clk = ~clk;

    // -- Main test sequence --
    initial begin
        // Waveform dump — disabled with -DNO_VCD for production runs
`ifndef NO_VCD
        $dumpfile("sobel.vcd");
        $dumpvars(0, sobel_tb);
`endif

        // Load input image
        $readmemh("input.hex", img_in);

        // Open output file
        out_file  = $fopen("output.hex", "w");
        out_count = 0;

        // Reset
        rst         = 1;
        pixel_in    = 0;
        pixel_valid = 0;
        feed_idx    = 0;

        @(posedge clk);
        @(posedge clk);
        rst = 0;
        @(posedge clk);

        // Stream all pixels, one per clock
        while (feed_idx < NUM_PIXELS) begin
            @(posedge clk);
            pixel_in    <= img_in[feed_idx];
            pixel_valid <= 1;
            feed_idx    = feed_idx + 1;
        end

        // De-assert valid and let the pipeline drain
        @(posedge clk);
        pixel_valid <= 0;

        // Wait extra cycles for the last output to emerge
        repeat (10) @(posedge clk);

        $fclose(out_file);
        $display("Simulation complete: %0d output pixels written to output.hex", out_count);
        $display("Expected: %0d  (= %0d x %0d)", (W-2)*(H-2), W-2, H-2);
        $finish;
    end

    // -- Capture output pixels on every out_valid --
    always @(posedge clk) begin
        if (out_valid) begin
            $fwrite(out_file, "%02X\n", pixel_out);
            out_count = out_count + 1;
        end
    end

endmodule

hdl/sobel.vcd
$date
	Sun May 10 11:38:25 2026
$end
$version
	Icarus Verilog
$end
$timescale
	1ps
$end
$scope module sobel_tb $end
$var wire 8 ! pixel_out [7:0] $end
$var wire 1 " out_valid $end
$var parameter 32 # H $end
$var parameter 64 $ NUM_PIXELS $end
$var parameter 32 % THRESHOLD $end
$var parameter 32 & W $end
$var reg 1 ' clk $end
$var reg 8 ( pixel_in [7:0] $end
$var reg 1 ) pixel_valid $end
$var reg 1 * rst $end
$var integer 32 + feed_idx [31:0] $end
$var integer 32 , out_count [31:0] $end
$var integer 32 - out_file [31:0] $end
$scope module dut $end
$var wire 1 ' clk $end
$var wire 8 . pixel_in [7:0] $end
$var wire 1 ) pixel_valid $end
$var wire 1 * rst $end
$var wire 12 / mag [11:0] $end
$var wire 12 0 gy [11:0] $end
$var wire 12 1 gx [11:0] $end
$var wire 12 2 abs_gy [11:0] $end
$var wire 12 3 abs_gx [11:0] $end
$var parameter 32 4 IMG_H $end
$var parameter 32 5 IMG_W $end
$var parameter 32 6 THRESHOLD $end
$var reg 16 7 col_cnt [15:0] $end
$var reg 1 " out_valid $end
$var reg 8 8 p00 [7:0] $end
$var reg 8 9 p01 [7:0] $end
$var reg 8 : p02 [7:0] $end
$var reg 8 ; p10 [7:0] $end
$var reg 8 < p11 [7:0] $end
$var reg 8 = p12 [7:0] $end
$var reg 8 > p20 [7:0] $end
$var reg 8 ? p21 [7:0] $end
$var reg 8 @ p22 [7:0] $end
$var reg 8 A pixel_out [7:0] $end
$var reg 16 B row_cnt [15:0] $end
$var reg 1 C win_filled $end
$var integer 32 D i [31:0] $end
$upscope $end
$upscope $end
$enddefinitions $end
$comment Show the parameter values. $end
$dumpall
b1010000 6
b1000000 5
b1000000 4
b1000000 &
b1010000 %
b1000000000000 $
b1000000 #
$end
#0
$dumpvars
bx D
xC
bx B
bx A
bx @
bx ?
bx >
bx =
bx <
bx ;
bx :
bx 9
bx 8
bx 7
bx 3
bx 2
bx 1
bx 0
bx /
b0 .
b10000000000000000000000000000011 -
b0 ,
b0 +
1*
0)
b0 (
0'
x"
bx !
$end
#5000
b0 /
b0 2
b0 3
b0 0
b0 1
0C
b0 @
b0 ?
b0 >
b0 =
b0 <
b0 ;
b0 :
b0 9
b0 8
b0 B
b0 7
0"
b0 !
b0 A
b1000000 D
1'
#10000
0'
#15000
0*
b1000000 D
1'
#20000
0'
#25000
1'
#30000
0'
#35000
1)
b101101 (
b101101 .
b1 +
1'
#40000
0'
#45000
b101101 3
b1011010 /
b101101 2
b1 7
b101101 1
b101101 0
b101101 @
b110010 (
b110010 .
b10 +
1'
#50000
0'
#55000
b110010 3
b10111110 /
b10001100 2
b101011 (
b101011 .
b10 7
b110010 1
b10001100 0
b110010 @
b101101 ?
b11 +
1'
#60000
0'
#65000
b10 3
b10111110 /
b10111100 2
b11 7
b101011 @
b110010 ?
b111111111110 1
b10111100 0
b101101 >
b100010 (
b100010 .
b100 +
1'
#70000
0'
#75000
b10000 3
b10111010 /
b10101010 2
b100011 (
b100011 .
b100 7
b100010 @
b101011 ?
b111111110000 1
b10101010 0
b110010 >
b101 +
1'
#80000
0'
#85000
b1000 3
b10011010 /
b10010010 2
b101 7
b100011 @
b100010 ?
b111111111000 1
b10010010 0
b101011 >
b101010 (
b101010 .
b110 +
1'
#90000
0'
#95000
b10011010 /
b10010010 2
b110100 (
b110100 .
b110 7
b101010 @
b100011 ?
b1000 1
b10010010 0
b100010 >
b111 +
1'
#100000
0'
#105000
b10001 3
b10111100 /
b10101011 2
b111 7
b110100 @
b101010 ?
b10001 1
b10101011 0
b100011 >
b110110 (
b110110 .
b1000 +
1'
#110000
0'
#115000
b1100 3
b11010100 /
b11001000 2
b1000 7
b110110 @
b110100 ?
b1100 1
b11001000 0
b101010 >
b1001 +
1'
#120000
0'
#125000
b10 3
b11011000 /
b11010110 2
b1001 7
b110110 ?
b10 1
b11010110 0
b110100 >
b110111 (
b110111 .
b1010 +
1'
#130000
0'
#135000
b1 3
b11011010 /
b11011001 2
b110011 (
b110011 .
b1010 7
b110111 @
b1 1
b11011001 0
b110110 >
b1011 +
1'
#140000
0'
#145000
b11 3
b11011010 /
b11010111 2
b1011 7
b111111111101 1
b11010111 0
b110011 @
b110111 ?
b101100 (
b101100 .
b1100 +
1'
#150000
0'
#155000
b1011 3
b11010100 /
b11001001 2
b101010 (
b101010 .
b1100 7
b101100 @
b110011 ?
b111111110101 1
b11001001 0
b110111 >
b1101 +
1'
#160000
0'
#165000
b1001 3
b10111110 /
b10110101 2
b1101 7
b101010 @
b101100 ?
b111111110111 1
b10110101 0
b110011 >
b101011 (
b101011 .
b1110 +
1'
#170000
0'
#175000
b1 3
b10101100 /
b10101011 2
b101100 (
b101100 .
b1110 7
b101011 @
b101010 ?
b111111111111 1
b10101011 0
b101100 >
b1111 +
1'
#180000
0'
#185000
b10 3
b10101110 /
b10101100 2
b1111 7
b101100 @
b101011 ?
b10 1
b10101100 0
b101010 >
b101101 (
b101101 .
b10000 +
1'
#190000
0'
#195000
b10110010 /
b10110000 2
b101110 (
b101110 .
b10000 7
b101101 @
b101100 ?
b10 1
b10110000 0
b101011 >
b10001 +
1'
#200000
0'
#205000
b10110110 /
b10110100 2
b10001 7
b101110 @
b101101 ?
b10 1
b10110100 0
b101100 >
b101111 (
b101111 .
b10010 +
1'
#210000
0'
#215000
b10111010 /
b10111000 2
b110000 (
b110000 .
b10010 7
b101111 @
b101110 ?
b10 1
b10111000 0
b101101 >
b10011 +
1'
#220000
0'
#225000
b10111110 /
b10111100 2
b10011 7
b110000 @
b101111 ?
b10 1
b10111100 0
b101110 >
b101101 (
b101101 .
b10100 +
1'
#230000
0'
#235000
b10 3
b10111110 /
b10111100 2
b100100 (
b100100 .
b10100 7
b101101 @
b110000 ?
b111111111110 1
b10111100 0
b101111 >
b10101 +
1'
#240000
0'
#245000
b1100 3
b10111010 /
b10101110 2
b10101 7
b100100 @
b101101 ?
b111111110100 1
b10101110 0
b110000 >
b100010 (
b100010 .
b10110 +
1'
#250000
0'
#255000
b1011 3
b10100010 /
b10010111 2
b11100 (
b11100 .
b10110 7
b100010 @
b100100 ?
b111111110101 1
b10010111 0
b101101 >
b10111 +
1'
#260000
0'
#265000
b1000 3
b10001100 /
b10000100 2
b10111 7
b11100 @
b100010 ?
b111111111000 1
b10000100 0
b100100 >
b1101 (
b1101 .
b11000 +
1'
#270000
0'
#275000
b10101 3
b1111100 /
b1100111 2
b1110 (
b1110 .
b11000 7
b1101 @
b11100 ?
b111111101011 1
b1100111 0
b100010 >
b11001 +
1'
#280000
0'
#285000
b1110 3
b1010010 /
b1000100 2
b11001 7
b1110 @
b1101 ?
b111111110010 1
b1000100 0
b11100 >
b10100 (
b10100 .
b11010 +
1'
#290000
0'
#295000
b111 3
b1000100 /
b111101 2
b11010 7
b10100 @
b1110 ?
b111 1
b111101 0
b1101 >
b11011 +
1'
#300000
0'
#305000
b110 3
b1010000 /
b1001010 2
b11011 7
b10100 ?
b110 1
b1001010 0
b1110 >
b10011 (
b10011 .
b11100 +
1'
#310000
0'
#315000
b1 3
b1010000 /
b1001111 2
b10000 (
b10000 .
b11100 7
b10011 @
b111111111111 1
b1001111 0
b10100 >
b11101 +
1'
#320000
0'
#325000
b100 3
b1001110 /
b1001010 2
b11101 7
b111111111100 1
b1001010 0
b10000 @
b10011 ?
b1110 (
b1110 .
b11110 +
1'
#330000
0'
#335000
b101 3
b1000110 /
b1000001 2
b11001 (
b11001 .
b11110 7
b1110 @
b10000 ?
b111111111011 1
b1000001 0
b10011 >
b11111 +
1'
#340000
0'
#345000
b1001 3
b1001110 /
b1000101 2
b11111 7
b11001 @
b1110 ?
b1001 1
b1000101 0
b10000 >
b101010 (
b101010 .
b100000 +
1'
#350000
0'
#355000
b11100 3
b10000110 /
b1101010 2
b11110 (
b11110 .
b100000 7
b101010 @
b11001 ?
b11100 1
b1101010 0
b1110 >
b100001 +
1'
#360000
0'
#365000
b101 3
b10010000 /
b10001011 2
b100001 7
b11110 @
b101010 ?
b101 1
b10001011 0
b11001 >
b100001 (
b100001 .
b100010 +
1'
#370000
0'
#375000
b1001 3
b10010000 /
b10000111 2
b110001 (
b110001 .
b100010 7
b100001 @
b11110 ?
b111111110111 1
b10000111 0
b101010 >
b100011 +
1'
#380000
0'
#385000
b10011 3
b10100100 /
b10010001 2
b100011 7
b110001 @
b100001 ?
b10011 1
b10010001 0
b11110 >
b100101 (
b100101 .
b100100 +
1'
#390000
0'
#395000
b100 3
b10101100 /
b10101000 2
b100100 7
b100101 @
b110001 ?
b100 1
b10101000 0
b100001 >
b100101 +
1'
#400000
0'
#405000
b1100 3
b10101100 /
b10100000 2
b100101 7
b100101 ?
b111111110100 1
b10100000 0
b110001 >
b11101 (
b11101 .
b100110 +
1'
#410000
0'
#415000
b1000 3
b10010100 /
b10001100 2
b100101 (
b100101 .
b100110 7
b11101 @
b111111111000 1
b10001100 0
b100101 >
b100111 +
1'
#420000
0'
#425000
b0 3
b10000100 /
b10000100 2
b100111 7
b0 1
b10000100 0
b100101 @
b11101 ?
b110010 (
b110010 .
b101000 +
1'
#430000
0'
#435000
b10101 3
b10101110 /
b10011001 2
b11000 (
b11000 .
b101000 7
b110010 @
b100101 ?
b10101 1
b10011001 0
b11101 >
b101001 +
1'
#440000
0'
#445000
b1101 3
b10101110 /
b10100001 2
b101001 7
b11000 @
b110010 ?
b111111110011 1
b10100001 0
b100101 >
b100000 (
b100000 .
b101010 +
1'
#450000
0'
#455000
b10010 3
b10010100 /
b10000010 2
b100011 (
b100011 .
b101010 7
b100000 @
b11000 ?
b111111101110 1
b10000010 0
b110010 >
b101011 +
1'
#460000
0'
#465000
b1011 3
b10000110 /
b1111011 2
b101011 7
b100011 @
b100000 ?
b1011 1
b1111011 0
b11000 >
b101010 (
b101010 .
b101100 +
1'
#470000
0'
#475000
b1010 3
b10011010 /
b10010000 2
b110010 (
b110010 .
b101100 7
b101010 @
b100011 ?
b1010 1
b10010000 0
b100000 >
b101101 +
1'
#480000
0'
#485000
b1111 3
b10111000 /
b10101001 2
b101101 7
b110010 @
b101010 ?
b1111 1
b10101001 0
b100011 >
b101010 (
b101010 .
b101110 +
1'
#490000
0'
#495000
b0 3
b10111000 /
b10111000 2
b110010 (
b110010 .
b101110 7
b101010 @
b110010 ?
b0 1
b10111000 0
b101010 >
b101111 +
1'
#500000
0'
#505000
b10111000 /
b10111000 2
b101111 7
b110010 @
b101010 ?
b0 1
b10111000 0
b110010 >
b110011 (
b110011 .
b110000 +
1'
#510000
0'
#515000
b1001 3
b11001010 /
b11000001 2
b110000 7
b110011 @
b110010 ?
b1001 1
b11000001 0
b101010 >
b110001 +
1'
#520000
0'
#525000
b1 3
b11001100 /
b11001011 2
b110001 7
b110011 ?
b1 1
b11001011 0
b110010 >
b111000 (
b111000 .
b110010 +
1'
#530000
0'
#535000
b101 3
b11010110 /
b11010001 2
b100011 (
b100011 .
b110010 7
b111000 @
b101 1
b11010001 0
b110011 >
b110011 +
1'
#540000
0'
#545000
b10000 3
b11010110 /
b11000110 2
b110011 7
b111111110000 1
b11000110 0
b100011 @
b111000 ?
b10011 (
b10011 .
b110100 +
1'
#550000
0'
#555000
b100101 3
b10110110 /
b10010001 2
b110101 (
b110101 .
b110100 7
b10011 @
b100011 ?
b111111011011 1
b10010001 0
b111000 >
b110101 +
1'
#560000
0'
#565000
b10010 3
b10010000 /
b1111110 2
b110101 7
b110101 @
b10011 ?
b10010 1
b1111110 0
b100011 >
b1110011 (
b1110011 .
b110110 +
1'
#570000
0'
#575000
b1100000 3
b101010000 /
b11110000 2
b1111101 (
b1111101 .
b110110 7
b1110011 @
b110101 ?
b1100000 1
b11110000 0
b10011 >
b110111 +
1'
#580000
0'
#585000
b1001000 3
b111100000 /
b110011000 2
b110111 7
b1111101 @
b1110011 ?
b1001000 1
b110011000 0
b110101 >
b1110111 (
b1110111 .
b111000 +
1'
#590000
0'
#595000
b100 3
b111101000 /
b111100100 2
b10001101 (
b10001101 .
b111000 7
b1110111 @
b1111101 ?
b100 1
b111100100 0
b1110011 >
b111001 +
1'
#600000
0'
#605000
b10000 3
b1000001000 /
b111111000 2
b111001 7
b10001101 @
b1110111 ?
b10000 1
b111111000 0
b1111101 >
b10010110 (
b10010110 .
b111010 +
1'
#610000
0'
#615000
b11111 3
b1001000110 /
b1000100111 2
b10010010 (
b10010010 .
b111010 7
b10010110 @
b10001101 ?
b11111 1
b1000100111 0
b1110111 >
b111011 +
1'
#620000
0'
#625000
b101 3
b1001010000 /
b1001001011 2
b111011 7
b10010010 @
b10010110 ?
b101 1
b1001001011 0
b10001101 >
b10011000 (
b10011000 .
b111100 +
1'
#630000
0'
#635000
b10 3
b1001010100 /
b1001010010 2
b10010111 (
b10010111 .
b111100 7
b10011000 @
b10010010 ?
b10 1
b1001010010 0
b10010110 >
b111101 +
1'
#640000
0'
#645000
b101 3
b1001011110 /
b1001011001 2
b111101 7
b10010111 @
b10011000 ?
b101 1
b1001011001 0
b10010010 >
b10001011 (
b10001011 .
b111110 +
1'
#650000
0'
#655000
b1101 3
b1001011110 /
b1001010001 2
b10000011 (
b10000011 .
b111110 7
b10001011 @
b10010111 ?
b111111110011 1
b1001010001 0
b10011000 >
b111111 +
1'
#660000
0'
#665000
b10100 3
b1001000100 /
b1000110000 2
b111111 7
b10000011 @
b10001011 ?
b111111101100 1
b1000110000 0
b10010111 >
b10000101 (
b10000101 .
b1000000 +
1'
#670000
0'
#675000
b110 3
b1000011100 /
b1000010110 2
b101110 (
b101110 .
b1 B
b0 7
b10000101 @
b10000011 ?
b111111111010 1
b1000010110 0
b10001011 >
b1000001 +
1'
#680000
0'
#685000
b101 3
b111000000 /
b110111011 2
b1 7
b101110 @
b10000101 ?
b101 1
b110111011 0
b10000011 >
b101101 =
b110011 (
b110011 .
b1000010 +
1'
#690000
0'
#695000
b10010 3
b100100110 /
b100010100 2
b101011 (
b101011 .
b10 7
b110011 @
b101110 ?
b10010 1
b100010100 0
b10000101 >
b110010 =
b101101 <
b1000011 +
1'
#700000
0'
#705000
b111 3
b11000110 /
b10111111 2
b11 7
b101011 @
b110011 ?
b111111111001 1
b10111111 0
b101110 >
b101011 =
b110010 <
b101101 ;
b100010 (
b100010 .
b1000100 +
1'
#710000
0'
#715000
b110001 3
b11011100 /
b10101011 2
b100011 (
b100011 .
b100 7
b100010 @
b101011 ?
b111111001111 1
b10101011 0
b110011 >
b100010 =
b101011 <
b110010 ;
b1000101 +
1'
#720000
0'
#725000
b11000 3
b10101010 /
b10010010 2
b101 7
b100011 @
b100010 ?
b111111101000 1
b10010010 0
b101011 >
b100011 =
b100010 <
b101011 ;
b101100 (
b101100 .
b1000110 +
1'
#730000
0'
#735000
b10010100 2
b10101110 /
b11010 3
b110011 (
b110011 .
b110 7
b101100 @
b100011 ?
b11010 1
b10010100 0
b100010 >
b101010 =
b100011 <
b100010 ;
b1000111 +
1'
#740000
0'
#745000
b110010 3
b11100000 /
b10101110 2
b111 7
b110011 @
b101100 ?
b110010 1
b10101110 0
b100011 >
b110100 =
b101010 <
b100011 ;
b110101 (
b110101 .
b1001000 +
1'
#750000
0'
#755000
b100001 3
b11101000 /
b11000111 2
b110110 (
b110110 .
b1000 7
b110101 @
b110011 ?
b100001 1
b11000111 0
b101100 >
b110110 =
b110100 <
b101010 ;
b1001001 +
1'
#760000
0'
#765000
b111 3
b11011010 /
b11010011 2
b1001 7
b110110 @
b110101 ?
b111 1
b11010011 0
b110011 >
b110110 <
b110100 ;
b110111 (
b110111 .
b1001010 +
1'
#770000
0'
#775000
b100 3
b11011100 /
b11011000 2
b110100 (
b110100 .
b1010 7
b110111 @
b110110 ?
b100 1
b11011000 0
b110101 >
b110111 =
b110110 ;
b1001011 +
1'
#780000
0'
#785000
b1000 3
b11100000 /
b11011000 2
b1011 7
b110100 @
b110111 ?
b111111111000 1
b11011000 0
b110110 >
b110011 =
b110111 <
b101011 (
b101011 .
b1001100 +
1'
#790000
0'
#795000
b100010 3
b11101100 /
b11001010 2
b101010 (
b101010 .
b1100 7
b101011 @
b110100 ?
b111111011110 1
b11001010 0
b110111 >
b101100 =
b110011 <
b110111 ;
b1001101 +
1'
#800000
0'
#805000
b11100 3
b11010000 /
b10110100 2
b1101 7
b101010 @
b101011 ?
b111111100100 1
b10110100 0
b110100 >
b101010 =
b101100 <
b110011 ;
b101011 (
b101011 .
b1001110 +
1'
#810000
0'
#815000
b10 3
b10101100 /
b10101010 2
b101101 (
b101101 .
b1110 7
b101011 @
b101010 ?
b111111111110 1
b10101010 0
b101011 >
b101011 =
b101010 <
b101100 ;
b1001111 +
1'
#820000
0'
#825000
b111 3
b10110100 /
b10101101 2
b1111 7
b101101 @
b101011 ?
b111 1
b10101101 0
b101010 >
b101100 =
b101011 <
b101010 ;
b101110 (
b101110 .
b1010000 +
1'
#830000
0'
#835000
b10111010 /
b10110011 2
b10000 7
b101110 @
b101101 ?
b111 1
b10110011 0
b101011 >
b101101 =
b101100 <
b101011 ;
b1010001 +
1'
#840000
0'
#845000
b101 3
b10111100 /
b10110111 2
b10001 7
b101110 ?
b101 1
b10110111 0
b101101 >
b101110 =
b101101 <
b101100 ;
b110000 (
b110000 .
b1010010 +
1'
#850000
0'
#855000
b110 3
b11000000 /
b10111010 2
b101110 (
b101110 .
b10010 7
b110000 @
b110 1
b10111010 0
b101110 >
b101111 =
b101110 <
b101101 ;
b1010011 +
1'
#860000
0'
#865000
b100 3
b11000000 /
b10111100 2
b10011 7
b100 1
b10111100 0
b101110 @
b110000 ?
b110000 =
b101111 <
b101110 ;
b100111 (
b100111 .
b1010100 +
1'
#870000
0'
#875000
b1101 3
b11000000 /
b10110011 2
b100010 (
b100010 .
b10100 7
b100111 @
b101110 ?
b111111110011 1
b10110011 0
b110000 >
b101101 =
b110000 <
b101111 ;
b1010101 +
1'
#880000
0'
#885000
b100100 3
b11000010 /
b10011110 2
b10101 7
b100010 @
b100111 ?
b111111011100 1
b10011110 0
b101110 >
b100100 =
b101101 <
b110000 ;
b100011 (
b100011 .
b1010110 +
1'
#890000
0'
#895000
b11010 3
b10101000 /
b10001110 2
b11100 (
b11100 .
b10110 7
b100011 @
b100010 ?
b111111100110 1
b10001110 0
b100111 >
b100010 =
b100100 <
b101101 ;
b1010111 +
1'
#900000
0'
#905000
b10110 3
b10011010 /
b10000100 2
b10111 7
b11100 @
b100011 ?
b111111101010 1
b10000100 0
b100010 >
b11100 =
b100010 <
b100100 ;
b1110 (
b1110 .
b1011000 +
1'
#910000
0'
#915000
b111111 3
b10101000 /
b1101001 2
b11000 7
b1110 @
b11100 ?
b111111000001 1
b1101001 0
b100011 >
b1101 =
b11100 <
b100010 ;
b1011001 +
1'
#920000
0'
#925000
b101010 3
b1110000 /
b1000110 2
b11001 7
b1110 ?
b111111010110 1
b1000110 0
b11100 >
b1110 =
b1101 <
b11100 ;
b10011 (
b10011 .
b1011010 +
1'
#930000
0'
#935000
b10011 3
b1010000 /
b111101 2
b11010 7
b10011 @
b10011 1
b111101 0
b1110 >
b10100 =
b1110 <
b1101 ;
b1011011 +
1'
#940000
0'
#945000
b1000111 2
b1011000 /
b10001 3
b1000111 0
b10001 1
b11011 7
b10011 ?
b10100 <
b1110 ;
b10101 (
b10101 .
b1011100 +
1'
#950000
0'
#955000
b0 3
b1001110 /
b1001110 2
b10011 (
b10011 .
b11100 7
b10101 @
b0 1
b1001110 0
b10011 >
b10011 =
b10100 ;
b1011101 +
1'
#960000
0'
#965000
b1000 3
b1011000 /
b1010000 2
b11101 7
b111111111000 1
b1010000 0
b10011 @
b10101 ?
b10000 =
b10011 <
b1110 (
b1110 .
b1011110 +
1'
#970000
0'
#975000
b10001 3
b1011010 /
b1001001 2
b1011 (
b1011 .
b11110 7
b1110 @
b10011 ?
b111111101111 1
b1001001 0
b10101 >
b1110 =
b10000 <
b10011 ;
b1011111 +
1'
#980000
0'
#985000
b1010 3
b1000100 /
b111010 2
b11111 7
b1011 @
b1110 ?
b1010 1
b111010 0
b10011 >
b11001 =
b1110 <
b10000 ;
b1100 (
b1100 .
b1100000 +
1'
#990000
0'
#995000
b110110 3
b1100110 /
b110000 2
b100000 7
b1100 @
b1011 ?
b110110 1
b110000 0
b1110 >
b101010 =
b11001 <
b1110 ;
b1100001 +
1'
#1000000
0'
#1005000
b1011 3
b111010 /
b101111 2
b100001 7
b1100 ?
b1011 1
b101111 0
b1011 >
b11110 =
b101010 <
b11001 ;
b11100 (
b11100 .
b1100010 +
1'
#1010000
0'
#1015000
b10 3
b1000010 /
b1000000 2
b101101 (
b101101 .
b100010 7
b11100 @
b111111111110 1
b1000000 0
b1100 >
b100001 =
b11110 <
b101010 ;
b1100011 +
1'
#1020000
0'
#1025000
b1000111 3
b10111000 /
b1110001 2
b100011 7
b1000111 1
b1110001 0
b101101 @
b11100 ?
b110001 =
b100001 <
b11110 ;
b11000 (
b11000 .
b1100100 +
1'
#1030000
0'
#1035000
b100 3
b10010010 /
b10001110 2
b11001 (
b11001 .
b100100 7
b11000 @
b101101 ?
b100 1
b10001110 0
b11100 >
b100101 =
b110001 <
b100001 ;
b1100101 +
1'
#1040000
0'
#1045000
b101100 3
b10100010 /
b1110110 2
b100101 7
b11001 @
b11000 ?
b111111010100 1
b1110110 0
b101101 >
b100101 <
b110001 ;
b10111 (
b10111 .
b1100110 +
1'
#1050000
0'
#1055000
b10001 3
b1110010 /
b1100001 2
b101001 (
b101001 .
b100110 7
b10111 @
b11001 ?
b111111101111 1
b1100001 0
b11000 >
b11101 =
b100101 ;
b1100111 +
1'
#1060000
0'
#1065000
b10000 3
b10000000 /
b1110000 2
b100111 7
b101001 @
b10111 ?
b10000 1
b1110000 0
b11001 >
b100101 =
b11101 <
b110001 (
b110001 .
b1101000 +
1'
#1070000
0'
#1075000
b1000100 3
b11011110 /
b10011010 2
b11001 (
b11001 .
b101000 7
b110001 @
b101001 ?
b1000100 1
b10011010 0
b10111 >
b110010 =
b100101 <
b11101 ;
b1101001 +
1'
#1080000
0'
#1085000
b101010 3
b11001110 /
b10100100 2
b101001 7
b11001 @
b110001 ?
b111111010110 1
b10100100 0
b101001 >
b11000 =
b110010 <
b100101 ;
b100011 (
b100011 .
b1101010 +
1'
#1090000
0'
#1095000
b110010 3
b10111000 /
b10000110 2
b100010 (
b100010 .
b101010 7
b100011 @
b11001 ?
b111111001110 1
b10000110 0
b110001 >
b100000 =
b11000 <
b110010 ;
b1101011 +
1'
#1100000
0'
